README.md
setup.py
eha/__init__.py
eha.egg-info/PKG-INFO
eha.egg-info/SOURCES.txt
eha.egg-info/dependency_links.txt
eha.egg-info/entry_points.txt
eha.egg-info/requires.txt
eha.egg-info/top_level.txt
eha/agent/__init__.py
eha/agent/config.py
eha/agent/server.py
eha/agent/zmq_server.py
eha/client/__init__.py
eha/client/client.py
eha/proxy/__init__.py
eha/proxy/proxy.py